_cffi__x4dd961c9x6f134c66
_cffi__x5e3266c6x9e7bc695
_cffi__x7c8c3306x12e4e6a1
_cffi__x84e651a8xa2b2ad39
_cffi__x8a6db8dx18b4fa0c
_cffi__x971d94fdxc843d556
_cffi__xbefe79aex856559f1
_cffi__xe4856329xca02bf4d
_cffi__xe62d65bdxf05e97ef
bedup
